[{"line":2,"elements":[{"line":5,"name":"","description":"","type":"background","keyword":"Background","steps":[{"name":"url apiBaseURL","result":{"duration":13800,"status":"passed"},"match":{"location":"karate","arguments":[]},"keyword":"Given","line":6,"doc_string":{"content_type":"","value":"15:15:41.794 karate.env system property was: null \n","line":6}}]},{"line":8,"name":"check the status code is 200","description":"","id":"check-the-status-code-is-200","type":"scenario","keyword":"Scenario","steps":[{"name":"path 'tags'","result":{"duration":393700,"status":"passed"},"match":{"location":"karate","arguments":[]},"keyword":"Given","line":9},{"name":"method Get","result":{"duration":1646739500,"status":"passed"},"match":{"location":"karate","arguments":[]},"keyword":"When","line":10,"doc_string":{"content_type":"","value":"15:15:41.797 request:\n1 > GET https:\/\/conduit.productionready.io\/api\/tags\n1 > Authorization: Token eyJ0eXAiOiJKV1QiLCJhbGciOiJIUzI1NiJ9.eyJpZCI6MTgyMjE5LCJ1c2VybmFtZSI6InNhcmF0aGthcmF0ZSIsImV4cCI6MTYzMjY4MzczOX0.ZFGw_wbNINuPE8ZnuMSyrMCae7eUhS8a5_bSJG60ATM\n1 > Host: conduit.productionready.io\n1 > Connection: Keep-Alive\n1 > User-Agent: Apache-HttpClient\/4.5.13 (Java\/16.0.1)\n1 > Accept-Encoding: gzip,deflate\n\n\n15:15:43.442 response time in milliseconds: 1644\n1 < 200\n1 < Date: Wed, 28 Jul 2021 19:15:45 GMT\n1 < Content-Type: application\/json; charset=utf-8\n1 < Transfer-Encoding: chunked\n1 < Connection: keep-alive\n1 < Cache-Control: max-age=0, private, must-revalidate\n1 < ETag: W\/\"a6b87483548e21fcccbd524c319e85ce\"\n1 < Status: 200 OK\n1 < Vary: Origin\n1 < X-Content-Type-Options: nosniff\n1 < X-Frame-Options: SAMEORIGIN\n1 < X-Powered-By: Phusion Passenger 4.0.60\n1 < X-Request-Id: 9864bdf3-c56c-4779-bfd7-2d65364c7377\n1 < X-Runtime: 1.284400\n1 < X-XSS-Protection: 1; mode=block\n1 < CF-Cache-Status: DYNAMIC\n1 < Expect-CT: max-age=604800, report-uri=\"https:\/\/report-uri.cloudflare.com\/cdn-cgi\/beacon\/expect-ct\"\n1 < Report-To: {\"endpoints\":[{\"url\":\"https:\\\/\\\/a.nel.cloudflare.com\\\/report\\\/v3?s=NumHfKNr5zhKpRiClcQ3YgJ7fYzaePsKKzhxqkS%2Bt%2F3fpKuT2ADiSDLqPjiemks5PZlj2bOxhEGLp77ipi8bNziQMyYHSLXotmZRTiGxVetQ1c6YlQpiVBmgrpJ6rXjRBDixov80ea6Cuak0Lw%3D%3D\"}],\"group\":\"cf-nel\",\"max_age\":604800}\n1 < NEL: {\"report_to\":\"cf-nel\",\"max_age\":604800}\n1 < Server: cloudflare\n1 < CF-RAY: 676070184dac5a87-IAD\n1 < alt-svc: h3-27=\":443\"; ma=86400, h3-28=\":443\"; ma=86400, h3-29=\":443\"; ma=86400, h3=\":443\"; ma=86400\n{\"tags\":[\"\\u200C\",\"\\u200C\\u200C\",\"\\u200C\\u200C\\u200C\",\"\\u200C\\u200C\\u200C\\u200C\",\"\\u200C\\u200C\\u200C\\u200C\\u200C\\u200C\\u200C\",\"\\u200C\\u200C\\u200C\\u200C\\u200C\",\"\\u200C\\u200C\\u200C\\u200C\\u200C\\u200C\\u200C\\u200C\",\"\\u200C\\u200C\\u200C\\u200C\\u200C\\u200C\\u200C\\u200C\\u200C\\u200C\",\"\\u200C\\u200C\\u200C\\u200C\\u200C\\u200C\\u200C\\u200C\\u200C\\u200C\\u200C\",\"\\u200C\\u200C\\u200C\\u200C\\u200C\\u200C\",\"HuManIty\",\"Hu\\u200CMan\\u200CIty\",\"Gandhi\",\"HITLER\",\"SIDA\",\"BlackLivesMatter\",\"Black\\u200CLives\\u200CMatter\",\"test\",\"dragons\",\"butt\"]}\n","line":10}},{"name":"status 200","result":{"duration":10200,"status":"passed"},"match":{"location":"karate","arguments":[]},"keyword":"Then","line":11}],"tags":[{"name":"@debug","line":1}]},{"line":5,"name":"","description":"","type":"background","keyword":"Background","steps":[{"name":"url apiBaseURL","result":{"duration":16400,"status":"passed"},"match":{"location":"karate","arguments":[]},"keyword":"Given","line":6,"doc_string":{"content_type":"","value":"15:15:43.447 karate.env system property was: null \n","line":6}}]},{"line":14,"name":"Get all tags and verify data is present","description":"","id":"get-all-tags-and-verify-data-is-present","type":"scenario","keyword":"Scenario","steps":[{"name":"path 'tags'","result":{"duration":310600,"status":"passed"},"match":{"location":"karate","arguments":[]},"keyword":"Given","line":15},{"name":"method Get","result":{"duration":1421245800,"status":"passed"},"match":{"location":"karate","arguments":[]},"keyword":"When","line":16,"doc_string":{"content_type":"","value":"15:15:43.450 request:\n1 > GET https:\/\/conduit.productionready.io\/api\/tags\n1 > Authorization: Token eyJ0eXAiOiJKV1QiLCJhbGciOiJIUzI1NiJ9.eyJpZCI6MTgyMjE5LCJ1c2VybmFtZSI6InNhcmF0aGthcmF0ZSIsImV4cCI6MTYzMjY4MzczOX0.ZFGw_wbNINuPE8ZnuMSyrMCae7eUhS8a5_bSJG60ATM\n1 > Host: conduit.productionready.io\n1 > Connection: Keep-Alive\n1 > User-Agent: Apache-HttpClient\/4.5.13 (Java\/16.0.1)\n1 > Accept-Encoding: gzip,deflate\n\n\n15:15:44.870 response time in milliseconds: 1419\n1 < 200\n1 < Date: Wed, 28 Jul 2021 19:15:46 GMT\n1 < Content-Type: application\/json; charset=utf-8\n1 < Connection: keep-alive\n1 < Cache-Control: max-age=0, private, must-revalidate\n1 < ETag: W\/\"a6b87483548e21fcccbd524c319e85ce\"\n1 < Status: 200 OK\n1 < Vary: Origin\n1 < X-Content-Type-Options: nosniff\n1 < X-Frame-Options: SAMEORIGIN\n1 < X-Powered-By: Phusion Passenger 4.0.60\n1 < X-Request-Id: 3eec26fe-6187-497e-82fe-c98c3b05a1ee\n1 < X-Runtime: 1.072367\n1 < X-XSS-Protection: 1; mode=block\n1 < CF-Cache-Status: DYNAMIC\n1 < Expect-CT: max-age=604800, report-uri=\"https:\/\/report-uri.cloudflare.com\/cdn-cgi\/beacon\/expect-ct\"\n1 < Report-To: {\"endpoints\":[{\"url\":\"https:\\\/\\\/a.nel.cloudflare.com\\\/report\\\/v3?s=1MCCTrdAfbM4Y8I9GsCxXlAo0ZxdCCRspAx0Vbunx3z%2BUS%2Fu1ajKrbZfyB8gE6AHTHC8GP8DZpYTS%2FvuBYqwVUtYv8DgOPMgFHF9%2FQ7QNa%2FWKsgU5HSRMJjJ23n5RyIq1xHMRuMZCDq0WMA95A%3D%3D\"}],\"group\":\"cf-nel\",\"max_age\":604800}\n1 < NEL: {\"report_to\":\"cf-nel\",\"max_age\":604800}\n1 < Server: cloudflare\n1 < CF-RAY: 6760702299d3c1a2-IAD\n1 < alt-svc: h3-27=\":443\"; ma=86400, h3-28=\":443\"; ma=86400, h3-29=\":443\"; ma=86400, h3=\":443\"; ma=86400\n{\"tags\":[\"\\u200C\",\"\\u200C\\u200C\",\"\\u200C\\u200C\\u200C\",\"\\u200C\\u200C\\u200C\\u200C\",\"\\u200C\\u200C\\u200C\\u200C\\u200C\\u200C\\u200C\",\"\\u200C\\u200C\\u200C\\u200C\\u200C\",\"\\u200C\\u200C\\u200C\\u200C\\u200C\\u200C\\u200C\\u200C\",\"\\u200C\\u200C\\u200C\\u200C\\u200C\\u200C\\u200C\\u200C\\u200C\\u200C\",\"\\u200C\\u200C\\u200C\\u200C\\u200C\\u200C\\u200C\\u200C\\u200C\\u200C\\u200C\",\"\\u200C\\u200C\\u200C\\u200C\\u200C\\u200C\",\"HuManIty\",\"Hu\\u200CMan\\u200CIty\",\"Gandhi\",\"HITLER\",\"SIDA\",\"BlackLivesMatter\",\"Black\\u200CLives\\u200CMatter\",\"test\",\"dragons\",\"butt\"]}\n","line":16}},{"name":"match response.tags contains ['HITLER','SIDA']","result":{"duration":334800,"status":"passed"},"match":{"location":"karate","arguments":[]},"keyword":"Then","line":18},{"name":"match response.tags contains any ['meat','drink','Hu\u200CMan\u200CIty']","result":{"duration":500600,"status":"passed"},"match":{"location":"karate","arguments":[]},"keyword":"Then","line":19},{"name":"match response.tags !contains \"sarath\"","result":{"duration":871500,"status":"passed"},"match":{"location":"karate","arguments":[]},"keyword":"And","line":20},{"name":"match response.tags == \"#array\"","result":{"duration":344900,"status":"passed"},"match":{"location":"karate","arguments":[]},"keyword":"And","line":21},{"name":"match each response.tags == \"#string\"","result":{"duration":4077700,"status":"passed"},"match":{"location":"karate","arguments":[]},"keyword":"And","line":22}],"tags":[{"name":"@debug","line":1}]},{"line":5,"name":"","description":"","type":"background","keyword":"Background","steps":[{"name":"url apiBaseURL","result":{"duration":11400,"status":"passed"},"match":{"location":"karate","arguments":[]},"keyword":"Given","line":6,"doc_string":{"content_type":"","value":"15:15:44.881 karate.env system property was: null \n","line":6}}]},{"line":25,"name":"Get 5 articles from the page      #url use is https:\/\/conduit.productionready.io\/api\/articles?limit=5&offset=0","description":"","id":"get-5-articles-from-the-page------#url-use-is-https:--conduit.productionready.io-api-articles?limit=5&offset=0","type":"scenario","keyword":"Scenario","steps":[{"name":"def timeValidator = read('classpath:helpers\/timeValidator.js')","result":{"duration":7675800,"status":"passed"},"match":{"location":"karate","arguments":[]},"keyword":"*","line":26},{"name":"params {limit : 5, offset: 0}","result":{"duration":122100,"status":"passed"},"match":{"location":"karate","arguments":[]},"keyword":"Given","line":29},{"name":"path 'articles'","result":{"duration":366600,"status":"passed"},"match":{"location":"karate","arguments":[]},"keyword":"Given","line":30},{"name":"method Get","result":{"duration":961107200,"status":"passed"},"match":{"location":"karate","arguments":[]},"keyword":"When","line":31,"doc_string":{"content_type":"","value":"15:15:44.890 request:\n1 > GET https:\/\/conduit.productionready.io\/api\/articles?offset=0&limit=5\n1 > Authorization: Token eyJ0eXAiOiJKV1QiLCJhbGciOiJIUzI1NiJ9.eyJpZCI6MTgyMjE5LCJ1c2VybmFtZSI6InNhcmF0aGthcmF0ZSIsImV4cCI6MTYzMjY4MzczOX0.ZFGw_wbNINuPE8ZnuMSyrMCae7eUhS8a5_bSJG60ATM\n1 > Host: conduit.productionready.io\n1 > Connection: Keep-Alive\n1 > User-Agent: Apache-HttpClient\/4.5.13 (Java\/16.0.1)\n1 > Accept-Encoding: gzip,deflate\n\n\n15:15:45.850 response time in milliseconds: 959\n1 < 200\n1 < Date: Wed, 28 Jul 2021 19:15:47 GMT\n1 < Content-Type: application\/json; charset=utf-8\n1 < Transfer-Encoding: chunked\n1 < Connection: keep-alive\n1 < Cache-Control: max-age=0, private, must-revalidate\n1 < ETag: W\/\"ab1d25f21355b9ac8e133d00418cc05a\"\n1 < Status: 200 OK\n1 < Vary: Origin\n1 < X-Content-Type-Options: nosniff\n1 < X-Frame-Options: SAMEORIGIN\n1 < X-Powered-By: Phusion Passenger 4.0.60\n1 < X-Request-Id: 25f68470-a930-4d3c-aae1-ec51b602e2c8\n1 < X-Runtime: 0.643091\n1 < X-XSS-Protection: 1; mode=block\n1 < CF-Cache-Status: DYNAMIC\n1 < Expect-CT: max-age=604800, report-uri=\"https:\/\/report-uri.cloudflare.com\/cdn-cgi\/beacon\/expect-ct\"\n1 < Report-To: {\"endpoints\":[{\"url\":\"https:\\\/\\\/a.nel.cloudflare.com\\\/report\\\/v3?s=hIR1E86oz0S3AJEwdb1hgcs2lbyM2t1ceT4t6WKnNfvrzSqbxbFp2omYVAZVTOcarb3eQf1p%2Fwd6ygwI5VUYToFYClctrnRGr6pbgZeekzp63eb35BF3t06FxkICHh6KwgRgZg1uvPU7Jqgplg%3D%3D\"}],\"group\":\"cf-nel\",\"max_age\":604800}\n1 < NEL: {\"report_to\":\"cf-nel\",\"max_age\":604800}\n1 < Server: cloudflare\n1 < CF-RAY: 6760702b89b85b3b-IAD\n1 < alt-svc: h3-27=\":443\"; ma=86400, h3-28=\":443\"; ma=86400, h3-29=\":443\"; ma=86400, h3=\":443\"; ma=86400\n{\"articlesCount\":500,\"articles\":[{\"tagList\":[],\"createdAt\":\"2021-07-28T19:15:40.246Z\",\"author\":{\"image\":\"https:\\\/\\\/static.productionready.io\\\/images\\\/smiley-cyrus.jpg\",\"following\":false,\"bio\":null,\"username\":\"sarathkarate\"},\"description\":\"Father\",\"title\":\"Lead Research Representative\",\"body\":\"South Luis\",\"favoritesCount\":0,\"slug\":\"lead-research-representative-ieig87\",\"updatedAt\":\"2021-07-28T19:15:40.246Z\",\"favorited\":false},{\"tagList\":[],\"createdAt\":\"2021-07-28T19:15:08.373Z\",\"author\":{\"image\":\"https:\\\/\\\/static.productionready.io\\\/images\\\/smiley-cyrus.jpg\",\"following\":false,\"bio\":null,\"username\":\"sarathkarate\"},\"description\":\"Father\",\"title\":\"Principal Accounts Coordinator\",\"body\":\"Jaeville\",\"favoritesCount\":0,\"slug\":\"principal-accounts-coordinator-8wp0aw\",\"updatedAt\":\"2021-07-28T19:15:08.373Z\",\"favorited\":false},{\"tagList\":[],\"createdAt\":\"2021-07-28T19:12:53.479Z\",\"author\":{\"image\":\"https:\\\/\\\/static.productionready.io\\\/images\\\/smiley-cyrus.jpg\",\"following\":false,\"bio\":null,\"username\":\"sarathkarate\"},\"description\":\"Father\",\"title\":\"Lead Markets Specialist\",\"body\":\"North Ruebenville\",\"favoritesCount\":0,\"slug\":\"lead-markets-specialist-i90tdp\",\"updatedAt\":\"2021-07-28T19:12:53.479Z\",\"favorited\":false},{\"tagList\":[\"test-automation\",\"simple\",\"cypress\"],\"createdAt\":\"2021-07-28T19:06:01.089Z\",\"author\":{\"image\":\"https:\\\/\\\/static.productionready.io\\\/images\\\/smiley-cyrus.jpg\",\"following\":false,\"bio\":null,\"username\":\"cy276083635\"},\"description\":\"https:\\\/\\\/github.com\\\/helenanull\\\/cypress-example\",\"title\":\"Article created by Cypress test\",\"body\":\"This article is created with Cypress. See code here: https:\\\/\\\/github.com\\\/helenanull\\\/cypress-example\",\"favoritesCount\":0,\"slug\":\"article-created-by-cypress-test-kqkmmk\",\"updatedAt\":\"2021-07-28T19:06:01.089Z\",\"favorited\":false},{\"tagList\":[\"test-automation\",\"simple\",\"cypress\"],\"createdAt\":\"2021-07-28T19:05:15.998Z\",\"author\":{\"image\":\"https:\\\/\\\/static.productionready.io\\\/images\\\/smiley-cyrus.jpg\",\"following\":false,\"bio\":null,\"username\":\"cy972801750\"},\"description\":\"https:\\\/\\\/github.com\\\/helenanull\\\/cypress-example\",\"title\":\"Article created by Cypress test\",\"body\":\"This article is created with Cypress. See code here: https:\\\/\\\/github.com\\\/helenanull\\\/cypress-example\",\"favoritesCount\":1,\"slug\":\"article-created-by-cypress-test-d37rgu\",\"updatedAt\":\"2021-07-28T19:05:15.998Z\",\"favorited\":false}]}\n","line":31}},{"name":"status 200","result":{"duration":8800,"status":"passed"},"match":{"location":"karate","arguments":[]},"keyword":"Then","line":32},{"name":"match response.articles == '#[5]'","result":{"duration":1221000,"status":"passed"},"match":{"location":"karate","arguments":[]},"keyword":"And","line":34},{"name":"match response.articlesCount == 500","result":{"duration":378300,"status":"passed"},"match":{"location":"karate","arguments":[]},"keyword":"And","line":36},{"name":"match response.articles[*].author.bio contains null","result":{"duration":382900,"status":"passed"},"match":{"location":"karate","arguments":[]},"keyword":"And","line":41},{"name":"match response..bio contains null","result":{"duration":1052200,"status":"passed"},"match":{"location":"karate","arguments":[]},"keyword":"And","line":43},{"name":"match each response.articles ==","result":{"duration":15507600,"status":"passed"},"match":{"location":"karate","arguments":[]},"keyword":"And","line":46,"doc_string":{"content_type":"","value":"{\n        \"title\": \"#string\",\n        \"slug\": \"#string\",\n        \"body\": \"#string\",\n        \"createdAt\": \"#? timeValidator(_)\",\n        \"updatedAt\": \"#? timeValidator(_)\",\n        \"tagList\": \"#array\",\n        \"description\": \"#string\",\n        \"author\": {\n        \"username\": \"#string\",\n        \"bio\": \"##string\",\n        \"image\": \"#string\",\n        \"following\": \"#boolean\"\n        },\n        \"favorited\": \"#boolean\",\n        \"favoritesCount\": \"#number\"\n    }","line":46}}],"tags":[{"name":"@debug","line":1}]}],"name":"features\/HomePage.feature","description":"Home page tests","id":"home-page-tests","keyword":"Feature","uri":"features\/HomePage.feature","tags":[{"name":"@debug","line":1}]}]